deepview/vaal/__init__.py
deepview/vaal/camera.py
deepview/vaal/context.py
deepview/vaal/library.py
vaal-1.8.2.dist-info/LICENSE.txt
vaal-1.8.2.dist-info/METADATA
vaal-1.8.2.dist-info/WHEEL
vaal-1.8.2.dist-info/top_level.txt
vaal-1.8.2.dist-info/RECORD
