Metadata-Version: 2.1
Name: vaal
Version: 1.8.2
Summary: DeepView VAAL for Python
Home-page: https://embeddedml.com
Author: Au-Zone Technologies
Author-email: support@au-zone.com
License: PROPRIETARY
Platform: UNKNOWN
